{"is_source_file": false, "format": "", "description": "", "external_files": [], "external_methods": [], "published": [], "classes": [], "methods": [], "calls": [], "search-terms": [], "state": 2, "file_id": 16, "knowledge_revision": 33, "git_revision": "29a0619f7856524a2269faaef47cc6d98aaa3cc0", "hash": "4811ed0b2407729c0b2a8468e280a738", "format-version": 4, "code-base-name": "campus_helper_frontend", "filename": "campus_helper_frontend/README.md", "revision_history": [{"33": "29a0619f7856524a2269faaef47cc6d98aaa3cc0"}]}